setup.py
onetworedblue/__init__.py
onetworedblue/exportable_layout.py
onetworedblue/fct_file.py
onetworedblue/file_processor.py
onetworedblue/filebrowser.py
onetworedblue/fish_point.py
onetworedblue/fish_types.py
onetworedblue/image_size_data.py
onetworedblue/main.py
onetworedblue/onetworedblue.kv
onetworedblue/paint.py
onetworedblue/twofish.ico
onetworedblue/twofish.png
onetworedblue.egg-info/PKG-INFO
onetworedblue.egg-info/SOURCES.txt
onetworedblue.egg-info/dependency_links.txt
onetworedblue.egg-info/entry_points.txt
onetworedblue.egg-info/requires.txt
onetworedblue.egg-info/top_level.txt