Metadata-Version: 1.0
Name: onetworedblue
Version: 0.1.1
Summary: A tool for identifiying and counting benthic organisms in bottom photographs
Home-page: http://www.ericgallimore.com/projects/onetworedblue
Author: Eric Gallimore
Author-email: fishrock@ericgallimore.com
License: GPLv3+
Keywords: onetworedblue,fishrock,fish_rock,photographs,benthic
Platform: UNKNOWN
